README.md
license.txt
setup.py
Webscreaper_Chrome_Blaze.egg-info/PKG-INFO
Webscreaper_Chrome_Blaze.egg-info/SOURCES.txt
Webscreaper_Chrome_Blaze.egg-info/dependency_links.txt
Webscreaper_Chrome_Blaze.egg-info/top_level.txt
chrome_double/__init__.py
chrome_double/chrome_double_by_auto_dev.py
chrome_double/divs.py