Metadata-Version: 2.1
Name: Webscreaper-Chrome-Blaze
Version: 1.1
Summary: Este pacote loga no site da blazer e varre realizando um screaper limpo e sem trabalho algum do double
Author: Auto Dev
Author-email: ramonma31@gmail.com
Keywords: blaze,casino,webscreaper,selenium,sala de sinais
License-File: license.txt
